[{"question":"18. Qual das alternativas a seguir poderia representar a hipótese nula unicaudal para um teste t de amostras relacionadas?",
"type": "multiple_choice",
"answers":[{"answer":"a. $\mu_D < 0$", "correct": false, "feedback":"Incorreto. Leia o parágrafo acima novamente."},
{"answer":"b. $\mu_D ≠ 0$", "correct": false, "feedback":"Incorreto. Leia o parágrafo acima novamente."},
{"answer":"c. $\mu_1 = \mu_2$", "correct": false, "feedback":"Incorreto. Leia o parágrafo acima novamente."},
{"answer":"d. $\mu_D = 0$", "correct": true, "feedback":"Correto!"}]
}]